README.md
setup.py
alibabacloud_tea_fileform/__init__.py
alibabacloud_tea_fileform/client.py
alibabacloud_tea_fileform/file_form.py
alibabacloud_tea_fileform/models.py
alibabacloud_tea_fileform_py2.egg-info/PKG-INFO
alibabacloud_tea_fileform_py2.egg-info/SOURCES.txt
alibabacloud_tea_fileform_py2.egg-info/dependency_links.txt
alibabacloud_tea_fileform_py2.egg-info/requires.txt
alibabacloud_tea_fileform_py2.egg-info/top_level.txt