Metadata-Version: 1.1
Name: alibabacloud-tea-fileform-py2
Version: 0.0.2
Summary: The tea-fileform module of alibabaCloud Python2 SDK.
Home-page: https://github.com/aliyun/tea-fileform/tree/master/python2
Author: Alibaba Cloud
Author-email: alibaba-cloud-sdk-dev-team@list.alibaba-inc.com
License: Apache License 2.0
Keywords: alibabacloud,sdk,tea
Platform: any
Classifier: Development Status :: 5 - Production/Stable
Classifier: Intended Audience :: Developers
Classifier: License :: OSI Approved :: Apache Software License
Classifier: Programming Language :: Python :: 2
Classifier: Programming Language :: Python :: 2.7
Classifier: Topic :: Software Development
